package/interest.py
interest_loan_0.1-1.0.0.dist-info/LICENSE
interest_loan_0.1-1.0.0.dist-info/METADATA
interest_loan_0.1-1.0.0.dist-info/WHEEL
interest_loan_0.1-1.0.0.dist-info/top_level.txt
interest_loan_0.1-1.0.0.dist-info/RECORD
