Metadata-Version: 2.1
Name: interest-loan-0.1
Version: 1.0.0
Summary: A  Interest Calculator calculate loan interest rate etc.
Home-page: https://github.com/Akshay311/InterestCalc
Author: Akshay Thakare
Author-email: thakarea686@gmail.com
License: MIT
Platform: UNKNOWN
Classifier: License :: OSI Approved :: MIT License
Classifier: Programming Language :: Python :: 3
Classifier: Programming Language :: Python :: 3.7
License-File: LICENSE
